LICENSE
MANIFEST.in
README.rst
setup.cfg
setup.py
sql_data_dependency/__init__.py
sql_data_dependency/__init__.pyc
sql_data_dependency/command_line.py
sql_data_dependency/command_line.pyc
sql_data_dependency/sqldd.py
sql_data_dependency/sqldd.pyc
sqldd.egg-info/PKG-INFO
sqldd.egg-info/SOURCES.txt
sqldd.egg-info/dependency_links.txt
sqldd.egg-info/entry_points.txt
sqldd.egg-info/not-zip-safe
sqldd.egg-info/requires.txt
sqldd.egg-info/top_level.txt
tests/__init__.py
tests/conftest.py
tests/test_sqldd.py
tests/test_sqldd_live.py