Metadata-Version: 1.1
Name: sqldd
Version: 1.0.0
Summary: A toolkit for analyzing dependencies in SQL databases.
Home-page: http://github.com/rkeilty/sql-data-dependency
Author: Rick Keilty
Author-email: rkeilty@gmail.com
License: BSD
Platform: UNKNOWN
Classifier: Intended Audience :: Developers
Classifier: Intended Audience :: System Administrators
Classifier: Operating System :: OS Independent
Classifier: License :: OSI Approved :: BSD License
Classifier: Programming Language :: Python
Classifier: Topic :: Software Development
